setup.py
osconf/__init__.py
osconf.egg-info/PKG-INFO
osconf.egg-info/SOURCES.txt
osconf.egg-info/dependency_links.txt
osconf.egg-info/top_level.txt