Metadata-Version: 1.0
Name: osconf
Version: 0.1.3
Summary: Configure from environment variables
Home-page: https://github.com/gisce/osconf
Author: GISCE-TI, S.L.
Author-email: devel@gisce.net
License: MIT
Platform: UNKNOWN
